ws/rsspull/__init__.py
ws/rsspull/feed.py
ws/rsspull/maildir.py
ws/rsspull/main.py
ws/rsspull/util.py
ws/rsspull/tests/__init__.py
ws/rsspull/tests/test_feed.py
ws/rsspull/tests/test_main.py
ws/rsspull/tests/fixture/config
ws/rsspull/tests/fixture/feeds.opml
ws/rsspull/tests/fixture/ongoing.xml
ws/rsspull/tests/fixture/samruby.xml
ws.rsspull-2.5.0.dist-info/METADATA
ws.rsspull-2.5.0.dist-info/WHEEL
ws.rsspull-2.5.0.dist-info/entry_points.txt
ws.rsspull-2.5.0.dist-info/RECORD
