Metadata-Version: 2.1
Name: ws.rsspull
Version: 2.5.0
Summary: Downloads RSS/Atom feeds and converts them to Maildir messages
Project-URL: Repository, https://github.com/wosc/rsspull
Author-email: Wolfgang Schnerring <wosc@wosc.de>
License:  BSD-3-Clause
Requires-Python: >=3.7
Requires-Dist: feedparser
Requires-Dist: html2text
Requires-Dist: requests
Provides-Extra: test
Requires-Dist: pytest; extra == 'test'
Requires-Dist: pytest-cov; extra == 'test'
Requires-Dist: setuptools; extra == 'test'
